celery_redbeat-2.3.3.dist-info/licenses/AUTHORS
celery_redbeat-2.3.3.dist-info/licenses/LICENSE
redbeat/__init__.py
redbeat/decoder.py
redbeat/schedulers.py
redbeat/schedules.py
celery_redbeat-2.3.3.dist-info/METADATA
celery_redbeat-2.3.3.dist-info/WHEEL
celery_redbeat-2.3.3.dist-info/pbr.json
celery_redbeat-2.3.3.dist-info/top_level.txt
celery_redbeat-2.3.3.dist-info/RECORD
