Metadata-Version: 2.4
Name: celery-redbeat
Version: 2.3.3
Summary: A Celery Beat Scheduler using Redis for persistent storage
Home-page: https://github.com/sibson/redbeat
Author: Marc Sibson
License: Apache License, Version 2.0
Keywords: python, celery, beat, redis, scheduler
Classifier: Development Status :: 5 - Production/Stable
Classifier: License :: OSI Approved :: Apache Software License
Classifier: Topic :: System :: Distributed Computing
Classifier: Topic :: Software Development :: Object Brokering
Classifier: Programming Language :: Python
Classifier: Programming Language :: Python :: 3
Classifier: Programming Language :: Python :: 3.8
Classifier: Programming Language :: Python :: 3.9
Classifier: Programming Language :: Python :: 3.10
Classifier: Programming Language :: Python :: 3.11
Classifier: Programming Language :: Python :: 3.12
Classifier: Programming Language :: Python :: Implementation :: CPython
Classifier: Operating System :: OS Independent
Requires-Python: >=3.8
License-File: LICENSE
Requires-Dist: redis>=3.2
Requires-Dist: celery>=5.0
Requires-Dist: python-dateutil
Requires-Dist: tenacity
Requires-Dist: backports.zoneinfo>=0.2.1; python_version < "3.9.0"
Dynamic: author
Dynamic: description
Dynamic: keywords
Dynamic: license
Dynamic: license-file
